pyrcgeos/__init__.py
pyrcgeos/common.py
pyrcgeos/foliumap.py
pyrcgeos/pyrcgeos.py
pyrcgeos-0.0.3.dist-info/LICENSE
pyrcgeos-0.0.3.dist-info/METADATA
pyrcgeos-0.0.3.dist-info/WHEEL
pyrcgeos-0.0.3.dist-info/dependency_links.txt
pyrcgeos-0.0.3.dist-info/top_level.txt
pyrcgeos-0.0.3.dist-info/RECORD
