Metadata-Version: 2.1
Name: pyrcgeos
Version: 0.0.3
Summary: A python package for interactive mapping.
Home-page: https://github.com/rcgeos/pyrcgeos
Author: rcgeos
Author-email: renato.cumani4@gmail.com
License: MIT license
Keywords: pyrcgeos
Classifier: Development Status :: 2 - Pre-Alpha
Classifier: Intended Audience :: Developers
Classifier: License :: OSI Approved :: MIT License
Classifier: Natural Language :: English
Classifier: Programming Language :: Python :: 3
Classifier: Programming Language :: Python :: 3.7
Classifier: Programming Language :: Python :: 3.8
Classifier: Programming Language :: Python :: 3.9
Classifier: Programming Language :: Python :: 3.10
Requires-Python: >=3.7
License-File: LICENSE
Requires-Dist: folium
Requires-Dist: ipyleaflet
Requires-Dist: ipywidgets
Requires-Dist: geopandas
Requires-Dist: httpx
Requires-Dist: streamlit
